aviplot/FFFFFF.png
aviplot/__init__.py
aviplot/aviplot.py
aviplot/color_dicts.py
aviplot/markers.py
aviplot-1.0.2.dist-info/DESCRIPTION.rst
aviplot-1.0.2.dist-info/METADATA
aviplot-1.0.2.dist-info/RECORD
aviplot-1.0.2.dist-info/WHEEL
aviplot-1.0.2.dist-info/metadata.json
aviplot-1.0.2.dist-info/top_level.txt
gmplot/__init__.py
gmplot/color_dicts.py
gmplot/gmplot.py
gmplot/markers.py
