Metadata-Version: 2.0
Name: aviplot
Version: 1.0.2
Summary: Provide a matplotlib like interface to plotting data with Google Maps
Home-page: https://github.com/AvijitGhosh82/aviplot
Author: Avijit Ghosh
Author-email: avijitg22@gmail.com
License: MIT
Keywords: python wrapper google maps
Platform: UNKNOWN
Requires-Dist: requests
